<?xml version="1.0" encoding="UTF-8"?>
<rdf:RDF xmlns:rdf="http://www.w3.org/1999/02/22-rdf-syntax-ns#"
         xmlns:dc="http://purl.org/dc/elements/1.1/">
   <rdf:Description>
      <dc:title>The game of go: The national game of Japan</dc:title>
      <dc:creator>Arthur Smith (1870–1929)</dc:creator>
      <dc:publisher>Project Gutenberg, Urbana, Illinois, USA., 2021-10-30</dc:publisher>
      <dc:date>2021-10-30</dc:date>
      <dc:rights>This eBook is for the use of anyone anywhere at no cost and with almost no restrictions whatsoever. You may copy it, give it away or re-use it under the terms of the Project Gutenberg License included with this eBook or online at www.gutenberg.org.
This eBook is produced by the Online Distributed Proofreading Team at www.pgdp.net.
</dc:rights>
      <dc:subject>Go (Game)</dc:subject>
      <dc:identifier>pg:66632</dc:identifier>
   </rdf:Description>
</rdf:RDF>
